README.rst
setup.py
mnist/__init__.py
mnist/loader.py
mnist/__pycache__/__init__.cpython-34.pyc
mnist/__pycache__/loader.cpython-34.pyc
python_mnist.egg-info/PKG-INFO
python_mnist.egg-info/SOURCES.txt
python_mnist.egg-info/dependency_links.txt
python_mnist.egg-info/pbr.json
python_mnist.egg-info/top_level.txt