Metadata-Version: 1.1
Name: python-mnist
Version: 0.2
Summary: Simple MNIST data parser written in python
Home-page: https://github.com/sorki/python-mnist
Author: Richard Marko
Author-email: rmarko@fedoraproject.org
License: BSD
Platform: UNKNOWN
Classifier: Development Status :: 5 - Production/Stable
Classifier: Intended Audience :: Developers
Classifier: Operating System :: OS Independent
Classifier: Programming Language :: Python
